quackseq_limenqr/__init__.py
quackseq_limenqr/limenqr.py
quackseq_limenqr/limenqr_controller.py
quackseq_limenqr/limenqr_model.py
quackseq_limenqr-0.0.2.dist-info/METADATA
quackseq_limenqr-0.0.2.dist-info/WHEEL
quackseq_limenqr-0.0.2.dist-info/licenses/LICENSE
quackseq_limenqr-0.0.2.dist-info/RECORD
