Metadata-Version: 2.4
Name: quackseq-limenqr
Version: 0.0.2
Summary: Simple Python script to perform magnetic resonance spectroscopy experiments with the LimeSDR.
Project-URL: Homepage, https://nqrduck.cool
Project-URL: Bug Tracker, https://git.private.coffee/nqrduck/quackseq-limenqr/issues
Project-URL: Source Code, https://git.private.coffee/nqrduck/quackseq-limenqr
Author-email: jupfi <support@nqrduck.cool>
License: MIT License
License-File: LICENSE
Classifier: License :: OSI Approved :: MIT License
Classifier: Operating System :: OS Independent
Classifier: Programming Language :: Python :: 3
Requires-Python: >=3.10
Requires-Dist: h5py
Requires-Dist: limedriver
Requires-Dist: numpy
Requires-Dist: pyserial
Requires-Dist: quackseq
Requires-Dist: scipy
Provides-Extra: dev
Requires-Dist: black; extra == 'dev'
Requires-Dist: pydocstyle; extra == 'dev'
Requires-Dist: pyupgrade; extra == 'dev'
Requires-Dist: ruff; extra == 'dev'
